template_sense/__init__.py
template_sense/ai_payload_schema.py
template_sense/analyzer.py
template_sense/constants.py
template_sense/errors.py
template_sense/file_loader.py
template_sense/file_validation.py
template_sense/serialization.py
template_sense/adapters/__init__.py
template_sense/adapters/excel_adapter.py
template_sense/ai/__init__.py
template_sense/ai/base_classification.py
template_sense/ai/header_classification.py
template_sense/ai/line_item_extraction.py
template_sense/ai/table_column_classification.py
template_sense/ai/translation.py
template_sense/ai_providers/__init__.py
template_sense/ai_providers/anthropic_provider.py
template_sense/ai_providers/base_provider.py
template_sense/ai_providers/config.py
template_sense/ai_providers/factory.py
template_sense/ai_providers/interface.py
template_sense/ai_providers/openai_provider.py
template_sense/extraction/__init__.py
template_sense/extraction/header_candidates.py
template_sense/extraction/sheet_extractor.py
template_sense/extraction/summary_builder.py
template_sense/extraction/table_candidates.py
template_sense/extraction/table_header_detection.py
template_sense/mapping/__init__.py
template_sense/mapping/fuzzy_field_matching.py
template_sense/mapping/semantic_field_matching.py
template_sense/output/__init__.py
template_sense/output/canonical_aggregator.py
template_sense/output/normalized_output_builder.py
template_sense/pipeline/__init__.py
template_sense/pipeline/extraction_pipeline.py
template_sense/pipeline/stages/__init__.py
template_sense/pipeline/stages/ai_classification.py
template_sense/pipeline/stages/ai_payload_building.py
template_sense/pipeline/stages/ai_provider_setup.py
template_sense/pipeline/stages/base.py
template_sense/pipeline/stages/canonical_aggregation.py
template_sense/pipeline/stages/confidence_filtering.py
template_sense/pipeline/stages/file_loading.py
template_sense/pipeline/stages/fuzzy_matching.py
template_sense/pipeline/stages/grid_extraction.py
template_sense-0.1.1.dist-info/licenses/LICENSE
template_sense-0.1.1.dist-info/METADATA
template_sense-0.1.1.dist-info/WHEEL
template_sense-0.1.1.dist-info/top_level.txt
template_sense-0.1.1.dist-info/RECORD
