Metadata-Version: 2.4
Name: template-sense
Version: 0.1.1
Summary: AI-powered invoice template extraction library for Tako
Author-email: Babajide <jideokus.pm@gmail.com>
License: MIT
Project-URL: Homepage, https://github.com/Projects-with-Babajide/template-sense
Project-URL: Repository, https://github.com/Projects-with-Babajide/template-sense
Project-URL: Issues, https://github.com/Projects-with-Babajide/template-sense/issues
Keywords: invoice,template,extraction,ai,ocr,excel
Classifier: Development Status :: 3 - Alpha
Classifier: Intended Audience :: Developers
Classifier: License :: OSI Approved :: MIT License
Classifier: Programming Language :: Python :: 3
Classifier: Programming Language :: Python :: 3.10
Classifier: Programming Language :: Python :: 3.11
Classifier: Programming Language :: Python :: 3.12
Requires-Python: >=3.10
License-File: LICENSE
Requires-Dist: openpyxl>=3.1.0
Requires-Dist: openai>=1.0.0
Requires-Dist: anthropic>=0.18.0
Requires-Dist: python-dotenv>=1.0.0
Requires-Dist: rapidfuzz>=3.0.0
Provides-Extra: dev
Requires-Dist: pytest>=7.4.0; extra == "dev"
Requires-Dist: pytest-cov>=4.1.0; extra == "dev"
Requires-Dist: black>=23.0.0; extra == "dev"
Requires-Dist: ruff>=0.1.0; extra == "dev"
Requires-Dist: pre-commit>=3.5.0; extra == "dev"
Dynamic: license-file
